hidebound/__init__.py
hidebound/command.py
hidebound/core/__init__.py
hidebound/core/config.py
hidebound/core/connection.py
hidebound/core/database.py
hidebound/core/database_tools.py
hidebound/core/logging.py
hidebound/core/parser.py
hidebound/core/specification_base.py
hidebound/core/specifications.py
hidebound/core/tools.py
hidebound/core/traits.py
hidebound/core/validators.py
hidebound/exporters/__init__.py
hidebound/exporters/disk_exporter.py
hidebound/exporters/exporter_base.py
hidebound/exporters/girder_exporter.py
hidebound/exporters/s3_exporter.py
hidebound/py.typed
hidebound/server/__init__.py
hidebound/server/api.py
hidebound/server/app.py
hidebound/server/components.py
hidebound/server/extension.py
hidebound/server/extensions.py
hidebound/server/server_tools.py
hidebound/templates/style.css.j2
hidebound-0.34.2.dist-info/entry_points.txt
hidebound-0.34.2.dist-info/WHEEL
hidebound-0.34.2.dist-info/METADATA
hidebound-0.34.2.dist-info/licenses/LICENSE
hidebound-0.34.2.dist-info/RECORD
