Metadata-Version: 2.1
Name: hidebound
Version: 0.34.2
Summary: A MLOps framework for generating ML assets and metadata.
License: MIT
Keywords: ephemeral,database,asset,assetstore,datastore,vfx,mlops,ml,machine-learning,data
Author-email: Alex Braun <alexander.g.braun@gmail.com>
Requires-Python: >=3.9
Classifier: Development Status :: 4 - Beta
Classifier: Intended Audience :: Developers
Classifier: License :: OSI Approved :: MIT License
Classifier: Programming Language :: Python :: 3
Classifier: Programming Language :: Python :: 3.10
Classifier: Programming Language :: Python :: 3.9
Classifier: Typing :: Typed
Requires-Dist: boto3
Requires-Dist: botocore
Requires-Dist: click>=8.1.3
Requires-Dist: dash
Requires-Dist: dash-cytoscape>=0.2.0
Requires-Dist: dask[dataframe]<=2024.2.1
Requires-Dist: dask_gateway
Requires-Dist: distributed<=2024.2.1
Requires-Dist: flasgger
Requires-Dist: flask
Requires-Dist: flask-healthz
Requires-Dist: flask_healthz
Requires-Dist: girder-client
Requires-Dist: gunicorn>=21.2.0
Requires-Dist: jinja2>=3.0
Requires-Dist: json_logging
Requires-Dist: lunchbox
Requires-Dist: numpy
Requires-Dist: pandas>=2.1.0
Requires-Dist: pandasql
Requires-Dist: pyjson5
Requires-Dist: pyparsing>=3.0.1
Requires-Dist: pyyaml
Requires-Dist: requests
Requires-Dist: rolling-pin
Requires-Dist: schematics
Requires-Dist: scikit-image
Requires-Dist: sqlalchemy
Requires-Dist: werkzeug
Requires-Dist: wrapt
Project-URL: documentation, https://thenewflesh.github.io/hidebound
Project-URL: repository, https://github.com/theNewFlesh/hidebound
